pyrpgkit/__init__.py
pyrpgkit/action.py
pyrpgkit/actor.py
pyrpgkit/dialog.py
pyrpgkit/item.py
pyrpgkit/location.py
pyrpgkit/specialty.py
pyrpgkit/stat.py
pyrpgkit/turn.py
tests/__init__.py
tests/test_action.py
tests/test_actor.py
tests/test_dialog.py
pyrpgkit-0.0.2.dist-info/LICENCE
pyrpgkit-0.0.2.dist-info/METADATA
pyrpgkit-0.0.2.dist-info/WHEEL
pyrpgkit-0.0.2.dist-info/top_level.txt
pyrpgkit-0.0.2.dist-info/RECORD
